{
  "from": 411,
  "to": 420,
  "fetchedAt": "2026-07-23T13:32:14.929Z",
  "pages": [
    {
      "page": 411,
      "status": "ok",
      "sourceUrl": "https://www.kayttooh.je/mercedes/cl-class-2008/k%C3%A4ytt%C3%B6ohje?p=411",
      "imageUrl": "https://www.kayttooh.je/viewer/59/540359/411/bg19b.webp",
      "originalPath": "original/411.html",
      "title": "410",
      "en": "410\n Controls in detail\n Driving and parking\n For more information, see “Driving instructions” (\n 컄 page 539).\n Turn signals\n Combination switch\n 1 Turn signals, right\n 2 Turn signals, left\n 왘 Press the combination switch in the\n direction of arrow 1 or 2 .\n The corresponding turn signal indicator\n lamp L or K in the ins trume nt\n cluster flashes (\n 컄 page 30).\n The combination switch resets automatically after major steering wheel movements.\n Warning! G\n On slippery road surfaces, never downshift\n in order to obtain braking action. This could\n result in drive wheel slip and reduced vehicle control. Your vehicle’s ABS will not prevent this type of loss of control.\n Warning! G\n It is dangerous to shift the gear selector lever out of position P or N if th e engine s peed\n is higher than idle speed. If your foot is not\n firmly on the brake pedal, the vehicle could\n accelerate quickly forward or in reverse. You\n could lose control of the vehicle and hit\n someone or something. Only shift into gear\n when the engine is idling normally and when\n your right foot is firmly on the brake pedal.\n !\n Shift the automatic transmission to\n position P or R only when the vehic le is stopped\n in order to avoid damaging the transmission.\n !\n Do not run cold engine at high engine\n speeds. Running a cold engine at high engine\n speeds may shorten the service life of the engine. This is not covered by the Mercedes-Benz\n Limited Warranty\n CL 63 AM G and CL 65 AMG onl y:\n At engine temperatures below 68°F (20° C), the\n maximum speed is restricted in order to protect\n the engine. Avoid driving the vehicle at full speed\n while the engine is cold in order to prevent premature engine wear as well as diminished comfort.\n !\n Simultaneously depressing the accelerator\n pedal and applying the brakes reduces engine\n performance and causes premature brake wear\n and drivetrain wear which is not covered by the\n Mercedes-Benz Limited Warranty.\n 컄컄"
    },
    {
      "page": 412,
      "status": "ok",
      "sourceUrl": "https://www.kayttooh.je/mercedes/cl-class-2008/k%C3%A4ytt%C3%B6ohje?p=412",
      "imageUrl": "https://www.kayttooh.je/viewer/59/540359/412/bg19c.webp",
      "originalPath": "original/412.html",
      "title": "411",
      "en": "411\n Controls in detail\n Driving and parking\n Problems while driving\n The engine runs erratically and misfires\n • An ignition cable may be damaged.\n • The engine electronics may not be operating properly.\n • Unburned gasoline may have entered\n the catalytic converter and damaged it.\n 왘 Give very little gas.\n 왘 Have the problem repaired by an authorized Mercedes-Benz Center as\n soon as possible.\n The coolant temperature is above\n 248°F (120°C)\n The coolant is too hot and is no longer\n cooling the engine.\n 왘 Stop the vehicle in a safe location as\n soon as possible and turn off the engine. Allow engine and coolant to cool\n off.\n 왘 Check the coolant level and add coolant if necessary (\n 컄 page 559).\n In case of accident\n If the vehicle is leaking gasoline:\n 왘 Do not start the engine under any circumstances.\n 왘 Move away from vehicle.\n 왘 Notify local fire and/or police authorities.\n If the extent of the damage cannot be determined:\n 왘 Contact an authorized Mercedes-Benz\n Center or call Roadside Assistance.\n If no damage can be determined on the\n • major assemblies\n • fuel system\n • engine mount:\n 왘 Start the engine in the usual manner.\n i\n To signal minor directional changes such as\n changing lanes, press combination switch only\n to point of resistance and release. The corresponding turn signals will flash three times.\n i\n Excessive coolant temperatures trigger a\n warning message in the multifunction display\n (\n 컄 page 622)."
    },
    {
      "page": 413,
      "status": "ok",
      "sourceUrl": "https://www.kayttooh.je/mercedes/cl-class-2008/k%C3%A4ytt%C3%B6ohje?p=413",
      "imageUrl": "https://www.kayttooh.je/viewer/59/540359/413/bg19d.webp",
      "originalPath": "original/413.html",
      "title": "412",
      "en": "412\n Controls in detail\n Driving and parking\n Parking\n Electronic parking brake\n Warning! G\n With the engine not running, there is no\n power assistance for the brake and the\n steering systems. In this case, it is important to keep in mind that a considerably\n higher degree of effort is necessary to brake\n and steer the vehicle.\n Warning! G\n Do not park this vehicle in areas where combustible materials such as grass, hay, or\n leaves can come into contact with the hot\n exhaust system, as these materials could be\n ignited and cause a vehicle fire.\n To reduce the risk of personal injury as a result of vehicle movement, before turning off\n the engine and leaving the vehicle always:\n • Keep right foot on brake pedal.\n • Engage electronic parking brake.\n • Shift the automatic transmission to park\n position P .\n • Slowly release brake pedal.\n • When parked on an incline, turn front\n wheels towards the road curb.\n • Turn the SmartKey to starter switch\n position 0 and remove, or press\n KEYLESS-GO* start/stop button\n (\n 컄 page 366).\n • Take the SmartKey or the SmartKey with\n KEYLESS-GO* with you and lock vehicle\n when leaving.\n Warning! G\n When leaving the vehicle, always remove the\n SmartKey or SmartKey with KEYLESS-GO*\n from the starter switch, take it with you and\n lock the vehicle. Do not leave children unattended in the vehicle, or with access to an\n unlocked vehicle. Children could release the\n electronic parking brake and/or shift the\n automatic transmission out of park\n position P , eithe r of which co uld resul t in an\n accident and/or serious personal injury."
    },
    {
      "page": 414,
      "status": "ok",
      "sourceUrl": "https://www.kayttooh.je/mercedes/cl-class-2008/k%C3%A4ytt%C3%B6ohje?p=414",
      "imageUrl": "https://www.kayttooh.je/viewer/59/540359/414/bg19e.webp",
      "originalPath": "original/414.html",
      "title": "413",
      "en": "413\n Controls in detail\n Driving and parking\n 1 Handle for electronic parking brake\n Manually releasing electronic parking\n brake\n 왘 Pull han dle 1 .\n The red indicator lamp 0 (USA only)\n or ! (Canada only) in the instrument cluster goes out.\n You cannot release the electronic parking\n brake until the ignition is switched on.\n Automatically releasing electronic\n parking brake\n Your vehicle’s electronic parking brake is\n automatically released when:\n • The engine is running.\n • Tran smission is in dr ive posi tion D or\n reverse gear R .\n • The hood is closed.\n • You have fastened your seat belt.\n • You step on the accelerator pedal.\n If reverse gear R is engaged, the trunk\n must be closed.\n Warning! G\n Getting out of your vehicle with the automatic transmission not fully engaged in park\n position P is da ngerou s. Als o, wh en par ked\n on an inclin e, park positio n P alone may not\n prevent your vehicle from moving, possibly\n hitting people or objects.\n Always engage the electronic parking brake\n in ad diti on to shi ftin g to par k posi tion P\n (\n 컄 page 406).\n When parked on an incline, turn front wheels\n towards the road curb.\n i\n If you have not fastened your seat belt, the\n following conditions must be met in order for the\n electronic parking brake to be automatically released:\n • The driver’s door is closed.\n • You must move the gear selector out of park\n position P or drive faster than 2 mph\n (3 km/h)."
    },
    {
      "page": 415,
      "status": "ok",
      "sourceUrl": "https://www.kayttooh.je/mercedes/cl-class-2008/k%C3%A4ytt%C3%B6ohje?p=415",
      "imageUrl": "https://www.kayttooh.je/viewer/59/540359/415/bg19f.webp",
      "originalPath": "original/415.html",
      "title": "414",
      "en": "414\n Controls in detail\n Driving and parking\n Manually engaging electronic parking\n brake\n 왘 Press hand le 1 .\n The red indicator lamp 0 (USA only)\n or ! (Canada only) in the instrument cluster comes on.\n Automatically engaging electronic parking brake*\n Your vehicle’s electronic parking brake is\n automatically engaged when DISTRONIC\n Plus* (\n 컄 page 443) brings your vehicle to a\n standstill and at least one of the following\n conditions is met:\n • The engine is switched off.\n • The driver’s door is opened and the\n seat belt is not inserted in the belt\n buckle.\n • The hood is released.\n • The trunk lid is open while reverse\n gear R is engaged.\n • The vehicle is parked for an extended\n period of time.\n The red indicator la mp 0 in the instr ument cluster comes on.\n Emergency braking with electronic\n parking brake\n In an emergency situation, you can also\n brake your vehicle while driving by using\n the electronic parking brake.\n 왘 While driving, press handle for electronic parking brake (\n 컄 page 412).\n During the braking procedure, the red indicato r lam p 0 (USA only) or !\n (Canada only) flashes in the instrument\n cluster, the message “ Please Release Parking Brake ” appears on the multifunction\n display and you will hear a warning tone.\n Once the vehicle comes to a complete stop\n the electronic parking brake will engage.\n i\n You can also engage the electronic parking\n brake when the SmartKey is removed from the\n starter switch.\n i\n In addition to the electronic parking brake,\n park position P can be automatically engaged.\n i\n Your vehicle will be braked for as long as you\n press and hold the switch for the electronic parking brake. The longer you keep the electronic\n parking brake pressed, the more strongly your\n vehicle will be braked. This method occurs on all\n 4 wheels, not just the rear wheels."
    },
    {
      "page": 416,
      "status": "ok",
      "sourceUrl": "https://www.kayttooh.je/mercedes/cl-class-2008/k%C3%A4ytt%C3%B6ohje?p=416",
      "imageUrl": "https://www.kayttooh.je/viewer/59/540359/416/bg1a0.webp",
      "originalPath": "original/416.html",
      "title": "415",
      "en": "415\n Controls in detail\n Driving and parking\n Turning off the engine\n 왘 Shift the automatic transmission to\n park position P (\n 컄 page 421).\n Turning off with SmartKey\n 왘 Turn the SmartKey in the starter switch\n to position 0 (\n 컄 page 365) and remove\n it.\n The immobilizer is activated.\n Turning off with KEYLESS-GO*\n 왘 Press the KEYLESS-GO start/stop\n button (\n 컄 page 366) to turn off the engine.\n With the driver’s door closed, the starter sw itch is now in pos ition 1 . With the\n driver’s door opened, the starter switch\n is set to position 0 , same as SmartKey\n removed from starter switch\n (\n 컄 page 365).\n i\n If the engine cannot be turned off as described, see “Emergency engine shut-down”\n (\n 컄 page 717).\n Warning! G\n Do not turn off the engine before the vehicle\n has come to a complete stop. With the engine not running, there is no power assistance for the brake and steering systems. In\n this case, it is important to keep in mind that\n a considerably higher degree of effort is necessary to brake and steer the vehicle.\n !\n Observe instructions\n • when taking the vehicle through an\n automatic conveyor type car wash\n (\n 컄 page 598)\n • when towing the vehicle ( 컄 page 710)\n !\n If you turn off the engine using the\n SmartKey and\n • remove the SmartKey from the starter\n switch\n or\n • open a door\n the transmission will sh ift to park position P\n automatically.\n Keep in mind that turning off the engine with the\n SmartKey alone only will automatically shift the\n transmission to neutral position N .\n i\n In an emergency you can turn off the engine\n while driving by pressing and holding the\n KEYLESS-GO start/ stop button for\n approximately 3 seconds.\n !\n If you turn off the engine using the\n KEYLESS-GO start/stop button and open the\n driver’s or passenger door, the transmission will\n shift to park position P automatically.\n Keep in mind that turning off the engine using\n the KEYLESS-GO start/stop button alone only\n will automatically shift the transmission to\n neutral position N .\n 컄컄"
    },
    {
      "page": 417,
      "status": "ok",
      "sourceUrl": "https://www.kayttooh.je/mercedes/cl-class-2008/k%C3%A4ytt%C3%B6ohje?p=417",
      "imageUrl": "https://www.kayttooh.je/viewer/59/540359/417/bg1a1.webp",
      "originalPath": "original/417.html",
      "title": "416",
      "en": "416\n Controls in detail\n Driving and parking\n If you have started the engine with the\n KEYLESS-GO start/stop button and cannot turn it off as described above:\n 왘 Remove the KEYLESS-GO start/stop\n button from the starter switch.\n 왘 Insert the SmartKey with KEYLESS-GO\n into the starter switch.\n The engine turns off. The starter switch\n is in position 0 (\n 컄 page 365).\n Releasing seat belts\n 왘 Press the seat belt release button\n (\n 컄 page 389).\n Allow the retractor to completely rewind the seat belt by guiding the latch\n plate.\n i\n If you drive through an automatic conveyor\n type car wash, you can switch on the ignition\n with the KEYLESS-GO button and engage neutral\n position N or inser t the Sm artKe y into the s tarte r\n switch.\n !\n Make sure the seat belt retracts fully so that\n the seat belt and/or latch plate cannot get\n caught or pinched in the door or in the seat\n mechanism. This can damage the seat belt and\n impair the effectiveness of the seat belt, and/or\n cause damage to the door and/or door trim panel. Such damage is not covered by the\n Mercedes-Benz Limited Warranty.\n Damaged seat belts must be replaced. Contact\n an authorized Mercedes-Benz Center.\n 컄컄"
    },
    {
      "page": 418,
      "status": "ok",
      "sourceUrl": "https://www.kayttooh.je/mercedes/cl-class-2008/k%C3%A4ytt%C3%B6ohje?p=418",
      "imageUrl": "https://www.kayttooh.je/viewer/59/540359/418/bg1a2.webp",
      "originalPath": "original/418.html",
      "title": "417",
      "en": "417\n Controls in detail\n Automatic transmission\n 왔 Automatic transmission\n For more information on driving with an\n automatic transmission, see “Driving and\n parking” (\n 컄 page 406).\n Your vehicle’s transmission adapts its gear\n shifting process to your individual driving\n style by continually adjusting the shift\n points up or down. These shift point adjustments are performed based on current\n operating and driving conditions.\n If the operating conditions change, the\n automatic transmission reacts by\n adjusting its shift program.\n Gear selector lever\n The gear selector lever is located on the\n right of the steering column.\n Gearshift pattern for automatic\n transmission\n P Park position\n R Reverse gear\n N Neutral\n D Drive position\n i\n During the brief warm-up, transmission\n upshifting is delayed. This allows the catalytic\n converter to heat up more quickly to operating\n temperature.\n Warning! G\n Make sure that absolutely no objects are\n obstructing the pedals’ range of movement.\n Keep the driver’s footwell clear of all obstacles. If there are any floormats or carpets in\n the footwell, make sure that the pedals still\n have sufficient clearance.\n During sudden driving or braking maneuvers\n the objects could get caught between the\n pedals. You could then no longer brake or\n accelerate. This could lead to accidents and\n injury."
    },
    {
      "page": 419,
      "status": "ok",
      "sourceUrl": "https://www.kayttooh.je/mercedes/cl-class-2008/k%C3%A4ytt%C3%B6ohje?p=419",
      "imageUrl": "https://www.kayttooh.je/viewer/59/540359/419/bg1a3.webp",
      "originalPath": "original/419.html",
      "title": "418",
      "en": "418\n Controls in detail\n Automatic transmission\n Shifting from P to N\n Moving the gear selector lever up or down\n shifts the automatic transmission out of\n park position P :\n 왘 With the vehicle at a standstill, depress\n the brake pedal and keep it pressed.\n 왘 Move gear selector lever up or down to\n resistance point to select neutral\n position N .\n Shifting from N to R or from N to D\n 왘 With the vehicle at a standstill, depress\n the brake pedal and keep it pressed.\n 왘 Move gear selector lever up past the\n resistance point to select reverse\n gear R .\n or\n 왘 Move gear selector down past the\n resistance point to select drive\n position D .\n 왘 Release the brake pedal.\n 왘 Carefully depress the accelerator pedal\n to drive off when it is safe to do so.\n i\n The current transmission park position P , reverse ge ar R , neutral position N or drive\n position D appears in the multifunction display\n (\n 컄 page 421).\n Warning! G\n It is dangerous to shift the automatic transmission out of park posi tion P or neut ral\n position N if the engine speed i s high er th an\n idle speed. If your foot is not firmly on the\n brake pedal, the vehicle could accelerate\n quickly forward or reverse. You could lose\n control of the vehicle and hit someone or\n something. Only shift into gear when the\n engine is idling normally and when your right\n foot is firmly on the brake pedal.\n i\n The gear selector lever returns to its original\n position.\n i\n The gear selector lever returns to its original\n position.\n i\n When driving off, the electronic parking\n brake is released automatically (\n 컄 page 412)."
    },
    {
      "page": 420,
      "status": "ok",
      "sourceUrl": "https://www.kayttooh.je/mercedes/cl-class-2008/k%C3%A4ytt%C3%B6ohje?p=420",
      "imageUrl": "https://www.kayttooh.je/viewer/59/540359/420/bg1a4.webp",
      "originalPath": "original/420.html",
      "title": "419",
      "en": "419\n Controls in detail\n Automatic transmission\n Shifting from P to R\n 왘 With the vehicle at a standstill, depress\n the brake pedal and keep it pressed.\n 왘 Move gear selector lever up past the\n resistance point to select reverse\n gear R .\n 왘 Release the brake pedal.\n 왘 Carefully depress the accelerator pedal\n to drive off when it is safe to do so.\n Shifting from P to D\n 왘 With the vehicle at a standstill, depress\n the brake pedal and keep it pressed.\n 왘 Move gear selector lever down past the\n resistance point to select drive\n position D .\n 왘 Release the brake pedal.\n 왘 Carefully depress the accelerator pedal\n to drive off when it is safe to do so.\n Shifting from D, R, or N to P\n If you want to sele ct park position P with\n the transmission being in drive position D ,\n reverse ge ar R or neutral position N :\n 왘 With the vehicle at a standstill, depress\n the brake pedal and keep it pressed.\n 왘 Press the handle for electronic parking\n brake (\n 컄 page 412).\n 왘 Press button on gear selector lever in\n direction of arrow (\n 컄 page 417) to select park position P .\n 왘 Release the brake pedal.\n i\n The gear selector lever returns to its original\n position.\n i\n When driving off, the electronic parking\n brake is released automatically (\n 컄 page 412).\n i\n The gear selector lever returns to its original\n position.\n i\n When driving off, the electronic parking\n brake is released automatically (\n 컄 page 412).\n !\n Shift the automatic transmission directly\n from drive position D to re verse gear R , from\n reverse gear R to drive position D or directly to\n park position P only when the vehicle is stopped.\n Otherwise the automatic transmission could be\n damaged.\n When trying to free a vehicle stuck in mud or\n snow, see “Rocking the vehicle” (\n 컄 page 425)."
    }
  ]
}